ai_circuit_denoiser-1.0.0.dist-info/licenses/LICENSE
circuit_denoiser/__init__.py
circuit_denoiser/denoiser_engine.py
circuit_denoiser/main.py
circuit_denoiser/main_window.py
circuit_denoiser/model.py
circuit_denoiser/widgets/signal_plot.py
ai_circuit_denoiser-1.0.0.dist-info/METADATA
ai_circuit_denoiser-1.0.0.dist-info/WHEEL
ai_circuit_denoiser-1.0.0.dist-info/entry_points.txt
ai_circuit_denoiser-1.0.0.dist-info/top_level.txt
ai_circuit_denoiser-1.0.0.dist-info/RECORD
