Metadata-Version: 2.4
Name: ai-circuit-denoiser
Version: 1.0.0
Summary: AI-powered circuit signal denoising tool
Home-page: https://github.com/michaelforex277/AI-Circuit-Denoiser
Author: Michael Zhou
Author-email: Michael Zhou <your-email@example.com>
License: MIT
Project-URL: Homepage, https://github.com/michaelforex277/AI-Circuit-Denoiser
Project-URL: Bug Reports, https://github.com/michaelforex277/AI-Circuit-Denoiser/issues
Keywords: signal-processing,circuit,denoising,ai
Classifier: Development Status :: 4 - Beta
Classifier: Intended Audience :: Science/Research
Classifier: License :: OSI Approved :: MIT License
Classifier: Operating System :: OS Independent
Classifier: Programming Language :: Python :: 3
Classifier: Topic :: Scientific/Engineering
Requires-Python: >=3.8
License-File: LICENSE
Dynamic: author
Dynamic: home-page
Dynamic: license-file
Dynamic: requires-python
